{
    "league": "SPORTS",
    "games": [
        {
            "league": "SPORTS",
            "game": "Bernard Tomic vs Tristan Boyer",
            "away": "Bernard Tomic",
            "home": "Tristan Boyer",
            "time_raw": "7/21, 05:40PM",
            "markets": [
                {
                    "market": "Moneyline",
                    "pick": "Bernard Tomic",
                    "line": null,
                    "odds": "+155",
                    "handle": 92,
                    "bets": 67,
                    "edge": 25
                }
            ]
        },
        {
            "league": "SPORTS",
            "game": "Artur Gromek vs Mateusz Rutkowski",
            "away": "Artur Gromek",
            "home": "Mateusz Rutkowski",
            "time_raw": "7/21, 05:45PM",
            "markets": [
                {
                    "market": "Moneyline",
                    "pick": "Artur Gromek",
                    "line": null,
                    "odds": "+185",
                    "handle": 12,
                    "bets": 17,
                    "edge": -5
                }
            ]
        },
        {
            "league": "SPORTS",
            "game": "Pawel Adamus vs Sebastian Szostok",
            "away": "Pawel Adamus",
            "home": "Sebastian Szostok",
            "time_raw": "7/21, 05:45PM",
            "markets": [
                {
                    "market": "Moneyline",
                    "pick": "Pawel Adamus",
                    "line": null,
                    "odds": "+105",
                    "handle": 16,
                    "bets": 25,
                    "edge": -9
                }
            ]
        },
        {
            "league": "SPORTS",
            "game": "Hayato Matsuoka vs Daniel Milavsky",
            "away": "Hayato Matsuoka",
            "home": "Daniel Milavsky",
            "time_raw": "7/21, 05:45PM",
            "markets": [
                {
                    "market": "Moneyline",
                    "pick": "Hayato Matsuoka",
                    "line": null,
                    "odds": "+110",
                    "handle": 39,
                    "bets": 33,
                    "edge": 6
                }
            ]
        },
        {
            "league": "SPORTS",
            "game": "Jerzy Debski vs Zbigniew Nocun",
            "away": "Jerzy Debski",
            "home": "Zbigniew Nocun",
            "time_raw": "7/21, 05:55PM",
            "markets": [
                {
                    "market": "Moneyline",
                    "pick": "Jerzy Debski",
                    "line": null,
                    "odds": "+200",
                    "handle": 56,
                    "bets": 36,
                    "edge": 20
                }
            ]
        },
        {
            "league": "SPORTS",
            "game": "Alex Michelsen vs Arthur Gea",
            "away": "Alex Michelsen",
            "home": "Arthur Gea",
            "time_raw": "7/21, 06:00PM",
            "markets": [
                {
                    "market": "Moneyline",
                    "pick": "Alex Michelsen",
                    "line": null,
                    "odds": "+211",
                    "handle": 96,
                    "bets": 69,
                    "edge": 27
                }
            ]
        },
        {
            "league": "SPORTS",
            "game": "Marian Lebek vs Robert Szymik",
            "away": "Marian Lebek",
            "home": "Robert Szymik",
            "time_raw": "7/21, 06:00PM",
            "markets": [
                {
                    "market": "Moneyline",
                    "pick": "Marian Lebek",
                    "line": null,
                    "odds": "+100",
                    "handle": 23,
                    "bets": 60,
                    "edge": -37
                }
            ]
        },
        {
            "league": "SPORTS",
            "game": "Ladislav Havel 1956 vs Jan Potensky",
            "away": "Ladislav Havel 1956",
            "home": "Jan Potensky",
            "time_raw": "7/21, 06:00PM",
            "markets": [
                {
                    "market": "Moneyline",
                    "pick": "Ladislav Havel 1956",
                    "line": null,
                    "odds": "+125",
                    "handle": 100,
                    "bets": 100,
                    "edge": 0
                }
            ]
        },
        {
            "league": "SPORTS",
            "game": "Jakub Kuzmicz vs Jakub Glanowski",
            "away": "Jakub Kuzmicz",
            "home": "Jakub Glanowski",
            "time_raw": "7/21, 06:05PM",
            "markets": [
                {
                    "market": "Moneyline",
                    "pick": "Jakub Kuzmicz",
                    "line": null,
                    "odds": "+230",
                    "handle": 12,
                    "bets": 50,
                    "edge": -38
                }
            ]
        },
        {
            "league": "SPORTS",
            "game": "Wojciech Wojtaszczyk vs Jakub Pruszkowski",
            "away": "Wojciech Wojtaszczyk",
            "home": "Jakub Pruszkowski",
            "time_raw": "7/21, 06:10PM",
            "markets": [
                {
                    "market": "Moneyline",
                    "pick": "Wojciech Wojtaszczyk",
                    "line": null,
                    "odds": "+105",
                    "handle": 100,
                    "bets": 100,
                    "edge": 0
                }
            ]
        },
        {
            "league": "SPORTS",
            "game": "Jakub Skorupa vs Dariusz Molenda",
            "away": "Jakub Skorupa",
            "home": "Dariusz Molenda",
            "time_raw": "7/21, 06:20PM",
            "markets": [
                {
                    "market": "Moneyline",
                    "pick": "Jakub Skorupa",
                    "line": null,
                    "odds": "+475",
                    "handle": 100,
                    "bets": 100,
                    "edge": 0
                }
            ]
        },
        {
            "league": "SPORTS",
            "game": "Atletico Mineiro vs Bahia",
            "away": "Atletico Mineiro",
            "home": "Bahia",
            "time_raw": "7/21, 06:30PM",
            "markets": [
                {
                    "market": "Moneyline",
                    "pick": "Atletico Mineiro",
                    "line": null,
                    "odds": "+300",
                    "handle": 88,
                    "bets": 85,
                    "edge": 3
                },
                {
                    "market": "Spread",
                    "pick": "Atletico Mineiro -0.25",
                    "line": "+110",
                    "odds": "-0",
                    "handle": 0,
                    "bets": 0,
                    "edge": 0
                }
            ]
        },
        {
            "league": "SPORTS",
            "game": "Avai vs America Mineiro",
            "away": "Avai",
            "home": "America Mineiro",
            "time_raw": "7/21, 06:30PM",
            "markets": [
                {
                    "market": "Moneyline",
                    "pick": "Avai",
                    "line": "+230",
                    "odds": "+130",
                    "handle": 100,
                    "bets": 100,
                    "edge": 0
                }
            ]
        },
        {
            "league": "SPORTS",
            "game": "Novorizontino SP vs Criciuma",
            "away": "Novorizontino SP",
            "home": "Criciuma",
            "time_raw": "7/21, 06:30PM",
            "markets": [
                {
                    "market": "Moneyline",
                    "pick": "Novorizontino SP",
                    "line": "+275",
                    "odds": "+115",
                    "handle": 64,
                    "bets": 75,
                    "edge": -11
                }
            ]
        },
        {
            "league": "SPORTS",
            "game": "LA Dodgers @ PHI Phillies",
            "away": "LA Dodgers",
            "home": "PHI Phillies",
            "time_raw": "7/21, 06:40PM",
            "markets": [
                {
                    "market": "Moneyline",
                    "pick": "PHI Phillies",
                    "line": null,
                    "odds": "+100",
                    "handle": 33,
                    "bets": 48,
                    "edge": -15
                },
                {
                    "market": "Run Line",
                    "pick": "LA Dodgers -1.5",
                    "line": "+157",
                    "odds": "-1",
                    "handle": 49,
                    "bets": 59,
                    "edge": -10
                },
                {
                    "market": "Total",
                    "pick": "Over 9",
                    "line": null,
                    "odds": "—",
                    "handle": 44,
                    "bets": 40,
                    "edge": 4
                }
            ]
        },
        {
            "league": "SPORTS",
            "game": "MIN Twins @ CLE Guardians",
            "away": "MIN Twins",
            "home": "CLE Guardians",
            "time_raw": "7/21, 06:40PM",
            "markets": [
                {
                    "market": "Moneyline",
                    "pick": "CLE Guardians",
                    "line": null,
                    "odds": "+129",
                    "handle": 68,
                    "bets": 88,
                    "edge": -20
                },
                {
                    "market": "Run Line",
                    "pick": "CLE Guardians -1.5",
                    "line": "+136",
                    "odds": "-1",
                    "handle": 14,
                    "bets": 64,
                    "edge": -50
                },
                {
                    "market": "Total",
                    "pick": "Over 8",
                    "line": null,
                    "odds": "—",
                    "handle": 80,
                    "bets": 74,
                    "edge": 6
                }
            ]
        },
        {
            "league": "SPORTS",
            "game": "Mateusz Rutkowski vs Jakub Kuzmicz",
            "away": "Mateusz Rutkowski",
            "home": "Jakub Kuzmicz",
            "time_raw": "7/21, 06:50PM",
            "markets": [
                {
                    "market": "Moneyline",
                    "pick": "Mateusz Rutkowski",
                    "line": null,
                    "odds": "+100",
                    "handle": 0,
                    "bets": 0,
                    "edge": 0
                }
            ]
        },
        {
            "league": "SPORTS",
            "game": "Jan Potensky vs Vaclav Kosar",
            "away": "Jan Potensky",
            "home": "Vaclav Kosar",
            "time_raw": "7/21, 07:00PM",
            "markets": [
                {
                    "market": "Moneyline",
                    "pick": "Jan Potensky",
                    "line": null,
                    "odds": "+210",
                    "handle": 100,
                    "bets": 100,
                    "edge": 0
                }
            ]
        },
        {
            "league": "SPORTS",
            "game": "Jiri Louda vs Marcel Pikous",
            "away": "Jiri Louda",
            "home": "Marcel Pikous",
            "time_raw": "7/21, 07:00PM",
            "markets": [
                {
                    "market": "Moneyline",
                    "pick": "Jiri Louda",
                    "line": null,
                    "odds": "+105",
                    "handle": 0,
                    "bets": 0,
                    "edge": 0
                }
            ]
        },
        {
            "league": "SPORTS",
            "game": "Daniel Tuma vs Ales Bayer",
            "away": "Daniel Tuma",
            "home": "Ales Bayer",
            "time_raw": "7/21, 07:00PM",
            "markets": [
                {
                    "market": "Moneyline",
                    "pick": "Daniel Tuma",
                    "line": null,
                    "odds": "+110",
                    "handle": 100,
                    "bets": 100,
                    "edge": 0
                }
            ]
        },
        {
            "league": "SPORTS",
            "game": "Ladislav Havel 1956 vs Stanislav Mazanek",
            "away": "Ladislav Havel 1956",
            "home": "Stanislav Mazanek",
            "time_raw": "7/21, 07:30PM",
            "markets": [
                {
                    "market": "Moneyline",
                    "pick": "Ladislav Havel 1956",
                    "line": null,
                    "odds": "+330",
                    "handle": 42,
                    "bets": 67,
                    "edge": -25
                }
            ]
        },
        {
            "league": "SPORTS",
            "game": "Michal Regner vs Denis Hofman",
            "away": "Michal Regner",
            "home": "Denis Hofman",
            "time_raw": "7/21, 07:30PM",
            "markets": [
                {
                    "market": "Moneyline",
                    "pick": "Michal Regner",
                    "line": null,
                    "odds": "+120",
                    "handle": 54,
                    "bets": 50,
                    "edge": 4
                }
            ]
        },
        {
            "league": "SPORTS",
            "game": "NY Mets @ MIL Brewers",
            "away": "NY Mets",
            "home": "MIL Brewers",
            "time_raw": "7/21, 07:40PM",
            "markets": [
                {
                    "market": "Moneyline",
                    "pick": "MIL Brewers",
                    "line": null,
                    "odds": "+117",
                    "handle": 64,
                    "bets": 87,
                    "edge": -23
                },
                {
                    "market": "Run Line",
                    "pick": "MIL Brewers -1.5",
                    "line": "+145",
                    "odds": "-1",
                    "handle": 58,
                    "bets": 59,
                    "edge": -1
                },
                {
                    "market": "Total",
                    "pick": "Over 8.5",
                    "line": "8.5",
                    "odds": "+102",
                    "handle": 76,
                    "bets": 45,
                    "edge": 31
                }
            ]
        },
        {
            "league": "SPORTS",
            "game": "SF Giants @ KC Royals",
            "away": "SF Giants",
            "home": "KC Royals",
            "time_raw": "7/21, 07:40PM",
            "markets": [
                {
                    "market": "Moneyline",
                    "pick": "KC Royals",
                    "line": null,
                    "odds": "—",
                    "handle": 40,
                    "bets": 46,
                    "edge": -6
                },
                {
                    "market": "Run Line",
                    "pick": "SF Giants -1.5",
                    "line": "+144",
                    "odds": "-1",
                    "handle": 31,
                    "bets": 18,
                    "edge": 13
                },
                {
                    "market": "Total",
                    "pick": "Over 9",
                    "line": null,
                    "odds": "—",
                    "handle": 39,
                    "bets": 39,
                    "edge": 0
                }
            ]
        },
        {
            "league": "SPORTS",
            "game": "Wojciech Wojtaszczyk vs Pawel Adamus",
            "away": "Wojciech Wojtaszczyk",
            "home": "Pawel Adamus",
            "time_raw": "7/21, 07:45PM",
            "markets": [
                {
                    "market": "Moneyline",
                    "pick": "Wojciech Wojtaszczyk",
                    "line": null,
                    "odds": "+260",
                    "handle": 100,
                    "bets": 100,
                    "edge": 0
                }
            ]
        },
        {
            "league": "SPORTS",
            "game": "Shintaro Mochizuki vs Philip Sekulic",
            "away": "Shintaro Mochizuki",
            "home": "Philip Sekulic",
            "time_raw": "7/21, 08:00PM",
            "markets": [
                {
                    "market": "Moneyline",
                    "pick": "Shintaro Mochizuki",
                    "line": null,
                    "odds": "+215",
                    "handle": 92,
                    "bets": 91,
                    "edge": 1
                }
            ]
        },
        {
            "league": "SPORTS",
            "game": "Universidad Catolica [ECU] vs Barcelona SC",
            "away": "Universidad Catolica [ECU]",
            "home": "Barcelona SC",
            "time_raw": "7/21, 08:00PM",
            "markets": [
                {
                    "market": "Moneyline",
                    "pick": "Universidad Catolica [ECU]",
                    "line": null,
                    "odds": "+300",
                    "handle": 63,
                    "bets": 63,
                    "edge": 0
                }
            ]
        },
        {
            "league": "SPORTS",
            "game": "Vaclav Kosar vs Josef Pelikan",
            "away": "Vaclav Kosar",
            "home": "Josef Pelikan",
            "time_raw": "7/21, 08:00PM",
            "markets": [
                {
                    "market": "Moneyline",
                    "pick": "Vaclav Kosar",
                    "line": null,
                    "odds": "+150",
                    "handle": 100,
                    "bets": 100,
                    "edge": 0
                }
            ]
        },
        {
            "league": "SPORTS",
            "game": "Marcel Pikous vs Karel Schopf",
            "away": "Marcel Pikous",
            "home": "Karel Schopf",
            "time_raw": "7/21, 08:00PM",
            "markets": [
                {
                    "market": "Moneyline",
                    "pick": "Marcel Pikous",
                    "line": null,
                    "odds": "+140",
                    "handle": 100,
                    "bets": 100,
                    "edge": 0
                }
            ]
        },
        {
            "league": "SPORTS",
            "game": "Ales Bayer vs Matej Volf",
            "away": "Ales Bayer",
            "home": "Matej Volf",
            "time_raw": "7/21, 08:00PM",
            "markets": [
                {
                    "market": "Moneyline",
                    "pick": "Ales Bayer",
                    "line": null,
                    "odds": "+120",
                    "handle": 100,
                    "bets": 100,
                    "edge": 0
                }
            ]
        },
        {
            "league": "SPORTS",
            "game": "James McCabe vs Duncan Chan",
            "away": "James McCabe",
            "home": "Duncan Chan",
            "time_raw": "7/21, 08:00PM",
            "markets": [
                {
                    "market": "Moneyline",
                    "pick": "James McCabe",
                    "line": null,
                    "odds": "+135",
                    "handle": 69,
                    "bets": 80,
                    "edge": -11
                }
            ]
        },
        {
            "league": "SPORTS",
            "game": "Vaclav Kosar vs Josef Pelikan",
            "away": "Vaclav Kosar",
            "home": "Josef Pelikan",
            "time_raw": "7/21, 08:00PM",
            "markets": [
                {
                    "market": "Moneyline",
                    "pick": "Vaclav Kosar",
                    "line": null,
                    "odds": "+160",
                    "handle": 100,
                    "bets": 100,
                    "edge": 0
                }
            ]
        },
        {
            "league": "SPORTS",
            "game": "Marcel Pikous vs Karel Schopf",
            "away": "Marcel Pikous",
            "home": "Karel Schopf",
            "time_raw": "7/21, 08:00PM",
            "markets": [
                {
                    "market": "Moneyline",
                    "pick": "Marcel Pikous",
                    "line": null,
                    "odds": "+140",
                    "handle": 100,
                    "bets": 100,
                    "edge": 0
                }
            ]
        },
        {
            "league": "SPORTS",
            "game": "Ales Bayer vs Matej Volf",
            "away": "Ales Bayer",
            "home": "Matej Volf",
            "time_raw": "7/21, 08:00PM",
            "markets": [
                {
                    "market": "Moneyline",
                    "pick": "Ales Bayer",
                    "line": null,
                    "odds": "+110",
                    "handle": 100,
                    "bets": 100,
                    "edge": 0
                }
            ]
        },
        {
            "league": "SPORTS",
            "game": "DET Tigers @ CHI Cubs",
            "away": "DET Tigers",
            "home": "CHI Cubs",
            "time_raw": "7/21, 08:05PM",
            "markets": [
                {
                    "market": "Moneyline",
                    "pick": "CHI Cubs",
                    "line": null,
                    "odds": "+101",
                    "handle": 30,
                    "bets": 60,
                    "edge": -30
                },
                {
                    "market": "Run Line",
                    "pick": "CHI Cubs -1.5",
                    "line": "+168",
                    "odds": "-1",
                    "handle": 13,
                    "bets": 51,
                    "edge": -38
                },
                {
                    "market": "Total",
                    "pick": "Over 8",
                    "line": null,
                    "odds": "—",
                    "handle": 50,
                    "bets": 74,
                    "edge": -24
                }
            ]
        },
        {
            "league": "SPORTS",
            "game": "CHI White Sox @ TEX Rangers",
            "away": "CHI White Sox",
            "home": "TEX Rangers",
            "time_raw": "7/21, 08:05PM",
            "markets": [
                {
                    "market": "Moneyline",
                    "pick": "TEX Rangers",
                    "line": null,
                    "odds": "—",
                    "handle": 84,
                    "bets": 51,
                    "edge": 33
                },
                {
                    "market": "Run Line",
                    "pick": "CHI White Sox -1.5",
                    "line": "+155",
                    "odds": "-1",
                    "handle": 6,
                    "bets": 71,
                    "edge": -65
                },
                {
                    "market": "Total",
                    "pick": "Over 8.5",
                    "line": "8.5",
                    "odds": "—",
                    "handle": 100,
                    "bets": 87,
                    "edge": 13
                }
            ]
        },
        {
            "league": "SPORTS",
            "game": "MIA Marlins @ HOU Astros",
            "away": "MIA Marlins",
            "home": "HOU Astros",
            "time_raw": "7/21, 08:10PM",
            "markets": [
                {
                    "market": "Moneyline",
                    "pick": "HOU Astros",
                    "line": null,
                    "odds": "+105",
                    "handle": 27,
                    "bets": 63,
                    "edge": -36
                },
                {
                    "market": "Run Line",
                    "pick": "HOU Astros -1.5",
                    "line": "+158",
                    "odds": "-1",
                    "handle": 54,
                    "bets": 33,
                    "edge": 21
                },
                {
                    "market": "Total",
                    "pick": "Over 9",
                    "line": null,
                    "odds": "+102",
                    "handle": 78,
                    "bets": 53,
                    "edge": 25
                }
            ]
        },
        {
            "league": "SPORTS",
            "game": "Daniel Tuma vs Martin Sobisek",
            "away": "Daniel Tuma",
            "home": "Martin Sobisek",
            "time_raw": "7/21, 08:30PM",
            "markets": [
                {
                    "market": "Moneyline",
                    "pick": "Daniel Tuma",
                    "line": null,
                    "odds": "+135",
                    "handle": 76,
                    "bets": 67,
                    "edge": 9
                }
            ]
        },
        {
            "league": "SPORTS",
            "game": "Jiri Louda vs Denis Hofman",
            "away": "Jiri Louda",
            "home": "Denis Hofman",
            "time_raw": "7/21, 08:30PM",
            "markets": [
                {
                    "market": "Moneyline",
                    "pick": "Jiri Louda",
                    "line": null,
                    "odds": "+100",
                    "handle": 77,
                    "bets": 50,
                    "edge": 27
                }
            ]
        },
        {
            "league": "SPORTS",
            "game": "Jan Potensky vs Stanislav Mazanek",
            "away": "Jan Potensky",
            "home": "Stanislav Mazanek",
            "time_raw": "7/21, 08:30PM",
            "markets": [
                {
                    "market": "Moneyline",
                    "pick": "Jan Potensky",
                    "line": null,
                    "odds": "+265",
                    "handle": 70,
                    "bets": 50,
                    "edge": 20
                }
            ]
        },
        {
            "league": "SPORTS",
            "game": "Vila Nova vs Fortaleza CE",
            "away": "Vila Nova",
            "home": "Fortaleza CE",
            "time_raw": "7/21, 08:35PM",
            "markets": [
                {
                    "market": "Moneyline",
                    "pick": "Vila Nova",
                    "line": "+215",
                    "odds": "+155",
                    "handle": 100,
                    "bets": 100,
                    "edge": 0
                }
            ]
        },
        {
            "league": "SPORTS",
            "game": "WAS Nationals @ COL Rockies",
            "away": "WAS Nationals",
            "home": "COL Rockies",
            "time_raw": "7/21, 08:40PM",
            "markets": [
                {
                    "market": "Moneyline",
                    "pick": "COL Rockies",
                    "line": null,
                    "odds": "—",
                    "handle": 6,
                    "bets": 23,
                    "edge": -17
                },
                {
                    "market": "Run Line",
                    "pick": "WAS Nationals -1.5",
                    "line": "+132",
                    "odds": "-1",
                    "handle": 96,
                    "bets": 54,
                    "edge": 42
                },
                {
                    "market": "Total",
                    "pick": "Over 13.5",
                    "line": "13.5",
                    "odds": "—",
                    "handle": 92,
                    "bets": 36,
                    "edge": 56
                }
            ]
        },
        {
            "league": "SPORTS",
            "game": "Cruz Azul vs Puebla",
            "away": "Cruz Azul",
            "home": "Puebla",
            "time_raw": "7/21, 09:00PM",
            "markets": [
                {
                    "market": "Moneyline",
                    "pick": "Cruz Azul",
                    "line": null,
                    "odds": "+650",
                    "handle": 100,
                    "bets": 99,
                    "edge": 1
                }
            ]
        },
        {
            "league": "SPORTS",
            "game": "Josef Pelikan vs Ladislav Havel 1956",
            "away": "Josef Pelikan",
            "home": "Ladislav Havel 1956",
            "time_raw": "7/21, 09:00PM",
            "markets": [
                {
                    "market": "Moneyline",
                    "pick": "Josef Pelikan",
                    "line": null,
                    "odds": "+120",
                    "handle": 100,
                    "bets": 100,
                    "edge": 0
                }
            ]
        },
        {
            "league": "SPORTS",
            "game": "Karel Schopf vs Michal Regner",
            "away": "Karel Schopf",
            "home": "Michal Regner",
            "time_raw": "7/21, 09:00PM",
            "markets": [
                {
                    "market": "Moneyline",
                    "pick": "Karel Schopf",
                    "line": null,
                    "odds": "+140",
                    "handle": 0,
                    "bets": 0,
                    "edge": 0
                }
            ]
        },
        {
            "league": "SPORTS",
            "game": "STL Cardinals @ LA Angels",
            "away": "STL Cardinals",
            "home": "LA Angels",
            "time_raw": "7/21, 09:38PM",
            "markets": [
                {
                    "market": "Moneyline",
                    "pick": "LA Angels",
                    "line": null,
                    "odds": "—",
                    "handle": 41,
                    "bets": 33,
                    "edge": 8
                },
                {
                    "market": "Run Line",
                    "pick": "STL Cardinals -1.5",
                    "line": "+149",
                    "odds": "-1",
                    "handle": 89,
                    "bets": 28,
                    "edge": 61
                },
                {
                    "market": "Total",
                    "pick": "Over 9",
                    "line": null,
                    "odds": "+100",
                    "handle": 85,
                    "bets": 48,
                    "edge": 37
                }
            ]
        },
        {
            "league": "SPORTS",
            "game": "CIN Reds @ SEA Mariners",
            "away": "CIN Reds",
            "home": "SEA Mariners",
            "time_raw": "7/21, 09:40PM",
            "markets": [
                {
                    "market": "Moneyline",
                    "pick": "SEA Mariners",
                    "line": null,
                    "odds": "+101",
                    "handle": 7,
                    "bets": 47,
                    "edge": -40
                },
                {
                    "market": "Run Line",
                    "pick": "CIN Reds -1.5",
                    "line": "+166",
                    "odds": "-1",
                    "handle": 91,
                    "bets": 27,
                    "edge": 64
                },
                {
                    "market": "Total",
                    "pick": "Over 7.5",
                    "line": "7.5",
                    "odds": "—",
                    "handle": 36,
                    "bets": 68,
                    "edge": -32
                }
            ]
        },
        {
            "league": "SPORTS",
            "game": "Athletics @ ARI Diamondbacks",
            "away": "Athletics",
            "home": "ARI Diamondbacks",
            "time_raw": "7/21, 09:40PM",
            "markets": [
                {
                    "market": "Moneyline",
                    "pick": "ARI Diamondbacks",
                    "line": null,
                    "odds": "+114",
                    "handle": 100,
                    "bets": 85,
                    "edge": 15
                },
                {
                    "market": "Run Line",
                    "pick": "ARI Diamondbacks -1.5",
                    "line": "+144",
                    "odds": "-1",
                    "handle": 99,
                    "bets": 30,
                    "edge": 69
                },
                {
                    "market": "Total",
                    "pick": "Over 9.5",
                    "line": "9.5",
                    "odds": "—",
                    "handle": 44,
                    "bets": 37,
                    "edge": 7
                }
            ]
        },
        {
            "league": "SPORTS",
            "game": "Shintaro Mochizuki vs Philip Sekulic",
            "away": "Shintaro Mochizuki",
            "home": "Philip Sekulic",
            "time_raw": "7/21, 10:00PM",
            "markets": [
                {
                    "market": "Moneyline",
                    "pick": "Shintaro Mochizuki",
                    "line": null,
                    "odds": "+215",
                    "handle": 86,
                    "bets": 90,
                    "edge": -4
                }
            ]
        },
        {
            "league": "SPORTS",
            "game": "Toluca vs Pumas UNAM",
            "away": "Toluca",
            "home": "Pumas UNAM",
            "time_raw": "7/21, 11:00PM",
            "markets": [
                {
                    "market": "Moneyline",
                    "pick": "Toluca",
                    "line": null,
                    "odds": "+400",
                    "handle": 69,
                    "bets": 94,
                    "edge": -25
                }
            ]
        }
    ]
}